{
  "Goblins": [
    {
      "unit_type_id": "goblin_spearman",
      "display_name": "Goblin Spearman",
      "max_health": 1,
      "points_cost": 1,
      "abilities": {"id_results": {"MELEE": 1, "SAVE": 1}}
    },
    {
      "unit_type_id": "goblin_archer",
      "display_name": "Goblin Archer",
      "max_health": 1,
      "points_cost": 1,
      "abilities": {"id_results": {"MISSILE": 1}}
    }
  ],
  "Feral": [
    {
      "unit_type_id": "orc_archer",
      "display_name": "Orc Archer",
      "max_health": 2,
      "points_cost": 2,
      "abilities": {"id_results": {"MISSILE": 1}}
    },
    {
      "unit_type_id": "feral_wolf",
      "display_name": "Feral Wolf",
      "max_health": 1,
      "points_cost": 1,
      "abilities": {"id_results": {"MELEE": 1, "MANEUVER": 1}}
    }
  ],
  "Coral Elves": [
    {
      "unit_type_id": "elf_mage",
      "display_name": "Elf Mage",
      "max_health": 1,
      "points_cost": 3,
      "abilities": {"id_results": {"MAGIC": 1}, "sais": ["MAGIC_BOLT"]}
    },
    {
      "unit_type_id": "coral_elf_guardian",
      "display_name": "Coral Elf Guardian",
      "max_health": 2,
      "points_cost": 3,
      "abilities": {"id_results": {"SAVE": 2, "MELEE": 1}}
    }
  ],
  "Dwarves": [
    {
      "unit_type_id": "dwarf_warrior",
      "display_name": "Dwarf Warrior",
      "max_health": 2,
      "points_cost": 2,
      "abilities": {"id_results": {"MELEE": 2}}
    },
    {
      "unit_type_id": "dwarf_axeman",
      "display_name": "Dwarf Axeman",
      "max_health": 2,
      "points_cost": 2,
      "abilities": {"id_results": {"MELEE": 2}}
    }
  ],
  "Firewalkers": [
    {
      "unit_type_id": "firewalker_initiate",
      "display_name": "Firewalker Initiate",
      "max_health": 1,
      "points_cost": 3,
      "abilities": {"id_results": {"MAGIC": 1}, "sais": ["MAGIC_BOLT"]}
    },
    {
      "unit_type_id": "firewalker_shaman",
      "display_name": "Firewalker Shaman",
      "max_health": 2,
      "points_cost": 4,
      "abilities": {"id_results": {"MAGIC": 2}, "sais": ["MAGIC_BOLT"]}
    }
  ],
  "Frostwings": [
    {
      "unit_type_id": "frostwing_hatchling",
      "display_name": "Frostwing Hatchling",
      "max_health": 2,
      "points_cost": 3,
      "abilities": {"id_results": {"MELEE": 1, "MAGIC": 1}, "sais": []}
    },
    {
      "unit_type_id": "frostwing_adult",
      "display_name": "Frostwing Adult",
      "max_health": 3,
      "points_cost": 5,
      "abilities": {"id_results": {"MELEE": 2, "MAGIC": 1}, "sais": ["BULLSEYE"]}
    }
  ],
  "Swamp Stalkers": [
    {
      "unit_type_id": "swamp_stalker_hunter",
      "display_name": "Swamp Stalker Hunter",
      "max_health": 1,
      "points_cost": 2,
      "abilities": {"id_results": {"MISSILE": 2}, "sais": []}
    }
  ],
  "Treefolk": [
    {
      "unit_type_id": "treefolk_sapling",
      "display_name": "Treefolk Sapling",
      "max_health": 3,
      "points_cost": 2,
      "abilities": {"id_results": {"SAVE": 2}}
    }
  ],
  "Undead": [
    {
      "unit_type_id": "undead_skeleton",
      "display_name": "Undead Skeleton",
      "max_health": 1,
      "points_cost": 1,
      "abilities": {"id_results": {"MELEE": 1}, "sais": ["RECRUIT"]}
    }
  ],
  "Amazons": [
    {
      "unit_type_id": "amazon_warrior",
      "display_name": "Amazon Warrior",
      "max_health": 2,
      "points_cost": 2,
      "abilities": {"id_results": {"MELEE": 1, "MISSILE": 1}}
    }
  ],
  "Lava Elves": [
    {
      "unit_type_id": "lava_elf_scout",
      "display_name": "Lava Elf Scout",
      "max_health": 1,
      "points_cost": 2,
      "abilities": {"id_results": {"MELEE": 1, "MANEUVER": 1}}
    }
  ],
  "Scalders": [
    {
      "unit_type_id": "scalders_berserker",
      "display_name": "Scalders Berserker",
      "max_health": 1,
      "points_cost": 2,
      "abilities": {"id_results": {"MELEE": 3}}
    }
  ]
}
